vcdparser/__init__.py
vcdparser/parser.py
vcdparser-0.1.0.dist-info/LICENSE
vcdparser-0.1.0.dist-info/METADATA
vcdparser-0.1.0.dist-info/WHEEL
vcdparser-0.1.0.dist-info/entry_points.txt
vcdparser-0.1.0.dist-info/top_level.txt
vcdparser-0.1.0.dist-info/RECORD
