Metadata-Version: 2.2
Name: vcdparser
Version: 0.1.0
License: MIT License
Project-URL: Homepage, https://github.com/menkalian/vcdparser
Project-URL: Repository, https://github.com/menkalian/vcdparser
Keywords: vcd,parser
Classifier: Programming Language :: Python :: 3
License-File: LICENSE
